{
  "_class": "MSImmutableHotspotLayer",
  "booleanOperation": -1,
  "do_objectID": "DFE4B9D9-F167-4EB9-A021-17B86DF433FC",
  "exportOptions": {
    "_class": "exportOptions",
    "exportFormats": [
    ],
    "includedLayerIds": [
    ],
    "layerOptions": 0,
    "shouldTrim": false
  },
  "flow": {
    "_class": "MSImmutableFlowConnection",
    "animationType": -1,
    "destinationArtboardID": "89F2C0CD-4DB9-4E2C-99C9-39A249CC2CB0",
    "do_objectID": "9551AB27-3D67-49A4-847E-1EBED7BC8D9E"
  },
  "frame": {
    "_class": "rect",
    "constrainProportions": false,
    "height": 222,
    "width": 220,
    "x": 772,
    "y": 207
  },
  "isFixedToViewport": false,
  "isFlippedHorizontal": false,
  "isFlippedVertical": false,
  "isLocked": false,
  "isVisible": true,
  "layerListExpandedType": 0,
  "maintainScrollPosition": false,
  "name": "Hotspot",
  "nameIsFixed": false,
  "resizingConstraint": 63,
  "resizingType": 0,
  "rotation": 0,
  "shouldBreakMaskChain": false
}