{
  "_class": "group",
  "booleanOperation": -1,
  "clippingMaskMode": 0,
  "do_objectID": "07817CA3-0C82-4663-AE2B-DF4ACEF8321B",
  "exportOptions": {
    "_class": "exportOptions",
    "do_objectID": "2844B1A3-1559-4E5D-8658-9F12D9982E00",
    "exportFormats": [
    ],
    "includedLayerIds": [
    ],
    "layerOptions": 0,
    "shouldTrim": false
  },
  "frame": {
    "_class": "rect",
    "constrainProportions": false,
    "do_objectID": "31AA3942-09B7-4FE3-828A-DD66A3E13446",
    "height": 180,
    "width": 150,
    "x": 0,
    "y": 0
  },
  "groupLayout": {
    "_class": "MSImmutableFreeformGroupLayout",
    "do_objectID": "9586F214-41AB-4FB0-9670-07D23E2BAC78"
  },
  "hasClickThrough": false,
  "hasClippingMask": false,
  "isFixedToViewport": false,
  "isFlippedHorizontal": false,
  "isFlippedVertical": false,
  "isLocked": false,
  "isVisible": true,
  "layerListExpandedType": 2,
  "layers": [
    {
      "class": "rectangle",
      "id": "E6A7463B-6B80-4958-B3FD-8CA50F1DF012"
    },
    {
      "class": "group",
      "id": "C61BCEBE-DF85-4A54-858C-F9101ADE8F51"
    },
    {
      "class": "rectangle",
      "id": "562635F1-1863-4200-8B50-ACC734648121"
    },
    {
      "class": "shapePath",
      "id": "3D8C8148-1693-48AF-B0B7-419BBCCCAB84"
    },
    {
      "class": "shapePath",
      "id": "E581FD87-7F5A-407E-9525-2360D7398549"
    },
    {
      "class": "text",
      "id": "787D842E-AFA0-46AC-9740-0322F34C76BB"
    },
    {
      "class": "text",
      "id": "28EB1706-4BEE-40BE-AA29-F8391F92F169"
    },
    {
      "class": "text",
      "id": "72EE5D07-4539-4ECA-8459-073740A4A5D0"
    }
  ],
  "maintainScrollPosition": false,
  "name": "Drop Down Menu",
  "nameIsFixed": true,
  "resizingConstraint": 63,
  "resizingType": 0,
  "rotation": 0,
  "shouldBreakMaskChain": false,
  "style": {
    "_class": "style",
    "blur": {
      "_class": "blur",
      "center": "{0.5, 0.5}",
      "isEnabled": false,
      "motionAngle": 0,
      "radius": 10,
      "saturation": 1,
      "type": 0
    },
    "borderOptions": {
      "_class": "borderOptions",
      "dashPattern": [
      ],
      "isEnabled": true,
      "lineCapStyle": 0,
      "lineJoinStyle": 0
    },
    "borders": [
    ],
    "colorControls": {
      "_class": "colorControls",
      "brightness": 0,
      "contrast": 1,
      "hue": 0,
      "isEnabled": true,
      "saturation": 1
    },
    "contextSettings": {
      "_class": "graphicsContextSettings",
      "blendMode": 0,
      "opacity": 1
    },
    "do_objectID": "3676CEFD-8188-4E2E-B101-718882A0A4CE",
    "endMarkerType": 0,
    "fills": [
    ],
    "innerShadows": [
    ],
    "miterLimit": 10,
    "shadows": [
    ],
    "startMarkerType": 0,
    "windingRule": 1
  }
}